optiseek/__init__.py
optiseek/metaheuristics.py
optiseek/modelhelpers.py
optiseek/testfunctions.py
optiseek/variables.py
optiseek-1.0.0.dist-info/LICENSE.md
optiseek-1.0.0.dist-info/WHEEL
optiseek-1.0.0.dist-info/METADATA
optiseek-1.0.0.dist-info/RECORD
