Metadata-Version: 2.1
Name: optiseek
Version: 1.0.0
Summary: A collection of single objective optimization algorithms for multi-dimensional functions.
Home-page: https://pypi.org/project/optiseek
License: MIT
Author: Alex Dundore
Author-email: acdundore.5@gmail.com
Requires-Python: >=3.9,<4.0
Classifier: License :: OSI Approved :: MIT License
Classifier: Programming Language :: Python :: 3
Classifier: Programming Language :: Python :: 3.10
Classifier: Programming Language :: Python :: 3.9
Requires-Dist: numpy (>=1.22.4,<2.0.0)
Requires-Dist: pandas (>=2.1.4,<3.0.0)
Project-URL: Documentation, https://acdundore.github.io/optiseek/
Project-URL: Repository, https://github.com/acdundore/optiseek
